platon_tester/__init__.py
platon_tester/constants.py
platon_tester/exceptions.py
platon_tester/main.py
platon_tester/rpc.py
platon_tester/backends/__init__.py
platon_tester/backends/base.py
platon_tester/backends/common.py
platon_tester/backends/mock/__init__.py
platon_tester/backends/mock/factory.py
platon_tester/backends/mock/main.py
platon_tester/backends/mock/serializers.py
platon_tester/backends/pyevm/__init__.py
platon_tester/backends/pyevm/main.py
platon_tester/backends/pyevm/serializers.py
platon_tester/backends/pyevm/utils.py
platon_tester/normalization/__init__.py
platon_tester/normalization/base.py
platon_tester/normalization/common.py
platon_tester/normalization/default.py
platon_tester/normalization/inbound.py
platon_tester/normalization/outbound.py
platon_tester/utils/__init__.py
platon_tester/utils/accounts.py
platon_tester/utils/address.py
platon_tester/utils/backend_testing.py
platon_tester/utils/emitter_contract.py
platon_tester/utils/encoding.py
platon_tester/utils/filters.py
platon_tester/utils/math_contract.py
platon_tester/utils/module_loading.py
platon_tester/utils/throws_contract.py
platon_tester/utils/transactions.py
platon_tester/validation/__init__.py
platon_tester/validation/base.py
platon_tester/validation/common.py
platon_tester/validation/default.py
platon_tester/validation/inbound.py
platon_tester/validation/outbound.py
platon_tester-1.2.0.dist-info/LICENSE
platon_tester-1.2.0.dist-info/METADATA
platon_tester-1.2.0.dist-info/WHEEL
platon_tester-1.2.0.dist-info/top_level.txt
platon_tester-1.2.0.dist-info/RECORD
