Metadata-Version: 2.1
Name: platon-tester
Version: 1.2.0
Summary: Tools for testing Platon applications.
Home-page: https://github.com/platonnetwork/platon-tester
Author: Shinnng
Author-email: Shinnng@outlook.com
License: MIT
Keywords: platon
Platform: UNKNOWN
Classifier: Development Status :: 2 - Pre-Alpha
Classifier: Intended Audience :: Developers
Classifier: License :: OSI Approved :: MIT License
Classifier: Natural Language :: English
Classifier: Programming Language :: Python :: 3
Classifier: Programming Language :: Python :: 3.6
Classifier: Programming Language :: Python :: 3.7
Classifier: Programming Language :: Python :: 3.8
Classifier: Programming Language :: Python :: 3.9
Requires-Python: >=3.6.8,<4
License-File: LICENSE
Requires-Dist: platon-abi (>=1.2.0)
Requires-Dist: platon-keys (>=1.2.0)
Requires-Dist: platon-utils (>=1.2.0)
Requires-Dist: rlp (<3,>=1.1.0)
Requires-Dist: semantic-version (<3.0.0,>=2.6.0)
Provides-Extra: dev
Requires-Dist: bumpversion (<1.0.0,>=0.5.3) ; extra == 'dev'
Requires-Dist: tox (<3.0.0,>=2.9.1) ; extra == 'dev'
Requires-Dist: wheel (<1.0.0,>=0.30.0) ; extra == 'dev'
Requires-Dist: pytest (<5.0.0,>=4.4.0) ; extra == 'dev'
Requires-Dist: pytest-xdist (<2,>=1.22.2) ; extra == 'dev'
Requires-Dist: platon-hash[pycryptodome] (>=1.2.0) ; extra == 'dev'
Requires-Dist: py-evm (==0.4.0a4) ; extra == 'dev'
Requires-Dist: flake8 (<4.0.0,>=3.5.0) ; extra == 'dev'
Requires-Dist: platon-hash[pysha3] (<1.0.0,>=0.1.4) ; (implementation_name == "cpython") and extra == 'dev'
Requires-Dist: platon-hash[pycryptodome] (<1.0.0,>=0.1.4) ; (implementation_name == "pypy") and extra == 'dev'
Provides-Extra: lint
Requires-Dist: flake8 (<4.0.0,>=3.5.0) ; extra == 'lint'
Provides-Extra: py-evm
Requires-Dist: py-evm (==0.4.0a4) ; extra == 'py-evm'
Requires-Dist: platon-hash[pysha3] (<1.0.0,>=0.1.4) ; (implementation_name == "cpython") and extra == 'py-evm'
Requires-Dist: platon-hash[pycryptodome] (<1.0.0,>=0.1.4) ; (implementation_name == "pypy") and extra == 'py-evm'
Provides-Extra: pyevm
Requires-Dist: py-evm (==0.4.0a4) ; extra == 'pyevm'
Requires-Dist: platon-hash[pysha3] (<1.0.0,>=0.1.4) ; (implementation_name == "cpython") and extra == 'pyevm'
Requires-Dist: platon-hash[pycryptodome] (<1.0.0,>=0.1.4) ; (implementation_name == "pypy") and extra == 'pyevm'
Provides-Extra: test
Requires-Dist: pytest (<5.0.0,>=4.4.0) ; extra == 'test'
Requires-Dist: pytest-xdist (<2,>=1.22.2) ; extra == 'test'
Requires-Dist: platon-hash[pycryptodome] (>=1.2.0) ; extra == 'test'
